setup.py
solWeek/__init__.py
solWeek/yearWeek.py
solWeek.egg-info/PKG-INFO
solWeek.egg-info/SOURCES.txt
solWeek.egg-info/dependency_links.txt
solWeek.egg-info/requires.txt
solWeek.egg-info/top_level.txt